{
	"name": "Excel4",
	"properties": {
		"linkedServiceName": {
			"referenceName": "AzureBlobStorage7",
			"type": "LinkedServiceReference"
		},
		"parameters": {
			"WorkSheet": {
				"type": "string"
			}
		},
		"annotations": [],
		"type": "Excel",
		"typeProperties": {
			"sheetName": {
				"value": "@dataset().WorkSheet",
				"type": "Expression"
			},
			"location": {
				"type": "AzureBlobStorageLocation",
				"fileName": "DataSample.xlsx",
				"container": "dataset"
			},
			"firstRowAsHeader": true
		},
		"schema": []
	}
}